brainfart/__init__.py
brainfart/_version.py
brainfart/config.py
brainfart/crypto.py
brainfart/embeddings.py
brainfart/extraction.py
brainfart/memory.py
brainfart/processor.py
brainfart/py.typed
brainfart/storage/__init__.py
brainfart/storage/faiss_store.py
brainfart/storage/sqlite_store.py
brainfart-0.3.0.dist-info/licenses/LICENSE
brainfart-0.3.0.dist-info/METADATA
brainfart-0.3.0.dist-info/WHEEL
brainfart-0.3.0.dist-info/top_level.txt
brainfart-0.3.0.dist-info/RECORD
