Metadata-Version: 2.4
Name: brainfart
Version: 0.3.0
Summary: Batteries-included memory for voice bots—FAISS + SQLite + embeddings + encryption in one pip install
Author-email: R1N Interactive <dev@r1n.ai>
License-Expression: BSD-2-Clause
Project-URL: Homepage, https://github.com/r1n-ai/brainfart
Project-URL: Documentation, https://github.com/r1n-ai/brainfart#readme
Project-URL: Repository, https://github.com/r1n-ai/brainfart.git
Project-URL: Bug Tracker, https://github.com/r1n-ai/brainfart/issues
Project-URL: Changelog, https://github.com/r1n-ai/brainfart/blob/main/CHANGELOG.md
Keywords: pipecat,memory,voice-ai,faiss,embeddings,rag,conversational-ai,encryption,brainfart
Classifier: Development Status :: 4 - Beta
Classifier: Intended Audience :: Developers
Classifier: Programming Language :: Python :: 3
Classifier: Programming Language :: Python :: 3.10
Classifier: Programming Language :: Python :: 3.11
Classifier: Programming Language :: Python :: 3.12
Classifier: Topic :: Scientific/Engineering :: Artificial Intelligence
Classifier: Typing :: Typed
Requires-Python: >=3.10
License-File: LICENSE
Requires-Dist: pipecat-ai>=0.0.67
Requires-Dist: faiss-cpu<2.0,>=1.8.0
Requires-Dist: fastembed<1.0,>=0.4.0
Requires-Dist: google-generativeai<1.0,>=0.8.0
Requires-Dist: pydantic<3.0,>=2.0.0
Requires-Dist: pydantic-settings<3.0,>=2.0.0
Requires-Dist: aiosqlite<1.0,>=0.19.0
Requires-Dist: numpy<3.0,>=1.21.0
Requires-Dist: cryptography<44.0,>=41.0.0
Requires-Dist: loguru<1.0,>=0.7.0
Provides-Extra: gpu
Requires-Dist: faiss-gpu-cu12<2.0,>=1.13.0; sys_platform == "linux" and extra == "gpu"
Provides-Extra: genai
Requires-Dist: google-genai<2.0,>=1.0.0; extra == "genai"
Provides-Extra: transformers
Requires-Dist: sentence-transformers<4.0,>=2.2.0; extra == "transformers"
Provides-Extra: dev
Requires-Dist: pytest<9.0,>=7.0.0; extra == "dev"
Requires-Dist: pytest-asyncio<1.0,>=0.21.0; extra == "dev"
Requires-Dist: pytest-cov<6.0,>=4.0.0; extra == "dev"
Requires-Dist: mypy<2.0,>=1.0.0; extra == "dev"
Requires-Dist: ruff<1.0,>=0.1.0; extra == "dev"
Dynamic: license-file
